rr_bot/__init__.py
rr_bot/__main__.py
rr_bot/bell.py
rr_bot/bot.py
rr_bot/calls.py
rr_bot/main.py
rr_bot/page_parser.py
rr_bot/regression.py
rr_bot/rhythm.py
rr_bot/tower.py
rr_bot/row_generation/__init__.py
rr_bot/row_generation/complib_composition_generator.py
rr_bot/row_generation/dixonoids_generator.py
rr_bot/row_generation/go_and_stop_calling_generator.py
rr_bot/row_generation/helpers.py
rr_bot/row_generation/method_place_notation_generator.py
rr_bot/row_generation/place_notation_generator.py
rr_bot/row_generation/plain_hunt_generator.py
rr_bot/row_generation/row_generator.py
tests/__init__.py
tests/row_generation/__init__.py
tests/row_generation/generator_test_helpers.py
tests/row_generation/test_DixonoidsGenerator.py
tests/row_generation/test_Helpers.py
tests/row_generation/test_MethodPlaceNotationGenerator.py
tests/row_generation/test_PlaceNotationGenerator.py
tests/row_generation/test_PlainHuntGenerator.py
rr_bot-0.1.1.dist-info/LICENSE
rr_bot-0.1.1.dist-info/METADATA
rr_bot-0.1.1.dist-info/WHEEL
rr_bot-0.1.1.dist-info/entry_points.txt
rr_bot-0.1.1.dist-info/top_level.txt
rr_bot-0.1.1.dist-info/RECORD
