Metadata-Version: 2.1
Name: rr-bot
Version: 0.1.1
Summary: A program that will fill in any set of bells in Ringing Room.
Home-page: https://github.com/Kneasle/ringing-room-bot/
Author: Ben White-Horne
Author-email: kneasle@gmail.com
License: MIT
Platform: any
Classifier: Programming Language :: Python :: 3
Classifier: License :: OSI Approved :: MIT License
Classifier: Operating System :: OS Independent
Requires-Python: >=3.6
Requires-Dist: numpy
Requires-Dist: requests
Requires-Dist: python-socketio
Requires-Dist: websocket-client
